{
  "status": "ok",
  "totalResults": 1,
  "articles": [
    {
      "source": { "id": null, "name": "NBCSports.com" },
      "author": "Curtis Crabtree",
      "title": "Bill Belichick thanks Tom Brady, calls him “best player in NFL history” - NBC Sports - NFL",
      "description": "Tom Brady may not have finished his career with the New England Patriots but he created most of his legacy during his 20 years with the franchise.After announcing his retirement on Tuesday, Patriots head coach Bill Belichick released a statement thanking Brad…",
      "url": "https://profootballtalk.nbcsports.com/2022/02/02/bill-belichick-thanks-tom-brady-calls-him-best-player-in-nfl-history/",
      "urlToImage": "https://profootballtalk.nbcsports.com/wp-content/uploads/sites/25/2022/02/GettyImages-1277316921-e1643859139241.jpg",
      "publishedAt": "2022-02-03T04:16:00Z",
      "content": "Tom Brady may not have finished his career with the New England Patriots but he created most of his legacy during his 20 years with the franchise.\r\nAfter announcing his retirement on Tuesday, Patriot… [+1148 chars]"
    }
  ]
}